htmlbook_docx/__init__.py
htmlbook_docx/document.py
htmlbook_docx/elements.py
htmlbook_docx/styles.py
htmlbook_docx-0.2.0.dist-info/METADATA
htmlbook_docx-0.2.0.dist-info/WHEEL
htmlbook_docx-0.2.0.dist-info/entry_points.txt
htmlbook_docx-0.2.0.dist-info/RECORD
