Metadata-Version: 2.3
Name: htmlbook-docx
Version: 0.2.0
Summary: Add your description here
Requires-Python: >=3.11
Requires-Dist: beautifulsoup4>=4.12.3
Requires-Dist: lxml>=5.3.0
Requires-Dist: python-docx>=1.1.2
Requires-Dist: typer>=0.12.5
